main.py
graphql_schema_mcp-0.9.1.dist-info/METADATA
graphql_schema_mcp-0.9.1.dist-info/WHEEL
graphql_schema_mcp-0.9.1.dist-info/entry_points.txt
graphql_schema_mcp-0.9.1.dist-info/top_level.txt
graphql_schema_mcp-0.9.1.dist-info/RECORD
