Metadata-Version: 2.4
Name: graphql-schema-mcp
Version: 0.9.1
Summary: Tiny MCP server to handle search in large GraphQL introspection files. Features vector search to improove experience.
Requires-Python: >=3.12
Requires-Dist: faiss-cpu>=1.11.0.post1
Requires-Dist: fastmcp>=2.11.2
Requires-Dist: sentence-transformers>=5.1.0
